nlp_rake/__init__.py
nlp_rake/algorithm.py
nlp_rake/stopwords.py
nlp_rake/utils.py
nlp_rake-0.0.2.dist-info/LICENSE
nlp_rake-0.0.2.dist-info/METADATA
nlp_rake-0.0.2.dist-info/WHEEL
nlp_rake-0.0.2.dist-info/top_level.txt
nlp_rake-0.0.2.dist-info/RECORD
