Metadata-Version: 2.1
Name: nlp-rake
Version: 0.0.2
Summary: Multilingual Rapid Automatic Keyword Extraction (RAKE) for Python
Home-page: https://github.com/malcolmvr/nlp_rake
Author: Vitaliy Grabovets
Author-email: vgithub@tryninja.io
License: MIT
Keywords: nlp,keywords,rake,keywords extraction
Platform: UNKNOWN
Requires-Python: >=3.5.0
Requires-Dist: langdetect (>=1.0.8)
Requires-Dist: numpy (>=1.14.4)
Requires-Dist: pyrsistent (>=0.14.2)
Requires-Dist: regex (>=2018.6.6)
